odoo8_addon_web_graph_improved-8.0.0.1.0.99.dev16-nspkg.pth
odoo_addons/web_graph_improved/README.md
odoo_addons/web_graph_improved/__init__.py
odoo_addons/web_graph_improved/__openerp__.py
odoo_addons/web_graph_improved/i18n/ar.po
odoo_addons/web_graph_improved/i18n/bg.po
odoo_addons/web_graph_improved/i18n/bs.po
odoo_addons/web_graph_improved/i18n/ca.po
odoo_addons/web_graph_improved/i18n/cs.po
odoo_addons/web_graph_improved/i18n/da.po
odoo_addons/web_graph_improved/i18n/de.po
odoo_addons/web_graph_improved/i18n/el_GR.po
odoo_addons/web_graph_improved/i18n/en_GB.po
odoo_addons/web_graph_improved/i18n/es.po
odoo_addons/web_graph_improved/i18n/es_AR.po
odoo_addons/web_graph_improved/i18n/es_BO.po
odoo_addons/web_graph_improved/i18n/es_CL.po
odoo_addons/web_graph_improved/i18n/es_CO.po
odoo_addons/web_graph_improved/i18n/es_CR.po
odoo_addons/web_graph_improved/i18n/es_DO.po
odoo_addons/web_graph_improved/i18n/es_EC.po
odoo_addons/web_graph_improved/i18n/es_MX.po
odoo_addons/web_graph_improved/i18n/es_PE.po
odoo_addons/web_graph_improved/i18n/es_PY.po
odoo_addons/web_graph_improved/i18n/es_VE.po
odoo_addons/web_graph_improved/i18n/et.po
odoo_addons/web_graph_improved/i18n/eu.po
odoo_addons/web_graph_improved/i18n/fa.po
odoo_addons/web_graph_improved/i18n/fi.po
odoo_addons/web_graph_improved/i18n/fr.po
odoo_addons/web_graph_improved/i18n/gl.po
odoo_addons/web_graph_improved/i18n/he.po
odoo_addons/web_graph_improved/i18n/hr.po
odoo_addons/web_graph_improved/i18n/hu.po
odoo_addons/web_graph_improved/i18n/id.po
odoo_addons/web_graph_improved/i18n/it.po
odoo_addons/web_graph_improved/i18n/ja.po
odoo_addons/web_graph_improved/i18n/ko.po
odoo_addons/web_graph_improved/i18n/lt.po
odoo_addons/web_graph_improved/i18n/lv.po
odoo_addons/web_graph_improved/i18n/mk.po
odoo_addons/web_graph_improved/i18n/mn.po
odoo_addons/web_graph_improved/i18n/nb.po
odoo_addons/web_graph_improved/i18n/nl.po
odoo_addons/web_graph_improved/i18n/nl_BE.po
odoo_addons/web_graph_improved/i18n/nl_NL.po
odoo8_addon_web_graph_improved-8.0.0.1.0.99.dev16.dist-info/METADATA
odoo8_addon_web_graph_improved-8.0.0.1.0.99.dev16.dist-info/WHEEL
odoo8_addon_web_graph_improved-8.0.0.1.0.99.dev16.dist-info/namespace_packages.txt
odoo8_addon_web_graph_improved-8.0.0.1.0.99.dev16.dist-info/top_level.txt
odoo8_addon_web_graph_improved-8.0.0.1.0.99.dev16.dist-info/RECORD
